wordnet_lookup/__init__.py
wordnet_lookup/find_wordnet.py
wordnet_lookup/os/__init__.py
wordnet_lookup/os/wordnet_a.py
wordnet_lookup/os/wordnet_b.py
wordnet_lookup/os/wordnet_c.py
wordnet_lookup/os/wordnet_d.py
wordnet_lookup/os/wordnet_e.py
wordnet_lookup/os/wordnet_f.py
wordnet_lookup/os/wordnet_g.py
wordnet_lookup/os/wordnet_h.py
wordnet_lookup/os/wordnet_i.py
wordnet_lookup/os/wordnet_j.py
wordnet_lookup/os/wordnet_k.py
wordnet_lookup/os/wordnet_l.py
wordnet_lookup/os/wordnet_m.py
wordnet_lookup/os/wordnet_n.py
wordnet_lookup/os/wordnet_o.py
wordnet_lookup/os/wordnet_p.py
wordnet_lookup/os/wordnet_q.py
wordnet_lookup/os/wordnet_r.py
wordnet_lookup/os/wordnet_s.py
wordnet_lookup/os/wordnet_t.py
wordnet_lookup/os/wordnet_u.py
wordnet_lookup/os/wordnet_v.py
wordnet_lookup/os/wordnet_w.py
wordnet_lookup/os/wordnet_x.py
wordnet_lookup/os/wordnet_y.py
wordnet_lookup/os/wordnet_z.py
wordnet_lookup-0.1.2.dist-info/WHEEL
wordnet_lookup-0.1.2.dist-info/METADATA
wordnet_lookup-0.1.2.dist-info/RECORD
